secmarker/MMlib3.py
secmarker/__init__.py
secmarker/_version.py
secmarker/argparse.py
secmarker/plot_tRNA.py
secmarker/secmarker_lib.py
secmarker/models/archaea.stk
secmarker/models/archaea.stk.cm
secmarker/models/bacteria.stk
secmarker/models/bacteria.stk.cm
secmarker/models/eukaryota.stk
secmarker/models/eukaryota.stk.cm
secmarker/models/tRNAsec_db.cm
secmarker/models/tRNAsec_db.stk
secmarker-0.4.1.dist-info/LICENSE
secmarker-0.4.1.dist-info/METADATA
secmarker-0.4.1.dist-info/WHEEL
secmarker-0.4.1.dist-info/top_level.txt
secmarker-0.4.1.dist-info/RECORD
