Metadata-Version: 2.1
Name: secmarker
Version: 0.4.1
Summary: secmarker description
Home-page: https://github.com/pypa/sampleproject
Author: Matteo Serrazanetti
Author-email: matteoserrazanetti@gmail.com
Classifier: Programming Language :: Python :: 3
Classifier: License :: OSI Approved :: MIT License
Classifier: Operating System :: OS Independent
Requires-Python: >=3.6
License-File: LICENSE
Requires-Dist: biopython (>=1.46)
Requires-Dist: networkx
